thumbtack/__init__.py
thumbtack/config.py
thumbtack/directory_monitoring.py
thumbtack/exceptions.py
thumbtack/resources.py
thumbtack/utils.py
thumbtack/views.py
thumbtack/static/css/thumbtack.css
thumbtack/static/js/thumbtack.js
thumbtack/templates/base.html
thumbtack/templates/form_complete.html
thumbtack/templates/index.html
thumbtack-0.5.8.dist-info/LICENSE
thumbtack-0.5.8.dist-info/METADATA
thumbtack-0.5.8.dist-info/WHEEL
thumbtack-0.5.8.dist-info/entry_points.txt
thumbtack-0.5.8.dist-info/top_level.txt
thumbtack-0.5.8.dist-info/RECORD
