Metadata-Version: 2.1
Name: thumbtack
Version: 0.5.8
Summary: Service to manage disk image mounts.
Home-page: https://github.com/mitre/thumbtack
Author: The MITRE Corporation
Author-email: thumbtack@mitre.org
License: Apache 2.0
Classifier: Development Status :: 4 - Beta
Classifier: Intended Audience :: Developers
Classifier: Topic :: Security
Classifier: Topic :: System :: Filesystems
Classifier: License :: OSI Approved :: Apache Software License
Classifier: Programming Language :: Python :: 3
Classifier: Programming Language :: Python :: 3.4
Classifier: Programming Language :: Python :: 3.5
Classifier: Programming Language :: Python :: 3.6
Classifier: Programming Language :: Python :: 3.7
Requires-Python: >=3.4.0
License-File: LICENSE
Requires-Dist: Click
Requires-Dist: Flask-RESTful
Requires-Dist: Flask ==3.0.3
Requires-Dist: gunicorn
Requires-Dist: imagemounter-mitre
Requires-Dist: requests
Provides-Extra: dev
Requires-Dist: bumpversion ; extra == 'dev'
Requires-Dist: coverage ; extra == 'dev'
Requires-Dist: pytest ; extra == 'dev'
Requires-Dist: pytest-cov ; extra == 'dev'
Requires-Dist: python-magic ; extra == 'dev'
Requires-Dist: pytsk3 ; extra == 'dev'
Requires-Dist: sphinx ; extra == 'dev'
Provides-Extra: docs
Requires-Dist: sphinx ; extra == 'docs'
Provides-Extra: test
Requires-Dist: coverage ; extra == 'test'
Requires-Dist: pytest ; extra == 'test'
Requires-Dist: pytest-cov ; extra == 'test'
